pyqt_top_left_right_file_list_widget/__init__.py
pyqt_top_left_right_file_list_widget/topLeftRightFileListWidget.py
pyqt_top_left_right_file_list_widget/ico/__init__.py
pyqt_top_left_right_file_list_widget/ico/add.svg
pyqt_top_left_right_file_list_widget/ico/clear.svg
pyqt_top_left_right_file_list_widget/ico/delete.svg
pyqt_top_left_right_file_list_widget-0.0.1.dist-info/LICENSE
pyqt_top_left_right_file_list_widget-0.0.1.dist-info/METADATA
pyqt_top_left_right_file_list_widget-0.0.1.dist-info/WHEEL
pyqt_top_left_right_file_list_widget-0.0.1.dist-info/top_level.txt
pyqt_top_left_right_file_list_widget-0.0.1.dist-info/RECORD
