Metadata-Version: 2.1
Name: pyqt-top-left-right-file-list-widget
Version: 0.0.1
Summary: Simple PyQt Widget which contains QListWidget and add, delete QPushButton to add and delete file in the list
Home-page: https://github.com/yjg30737/pyqt-top-left-right-file-list-widget.git
Author: Jung Gyu Yoon
Author-email: yjg30737@gmail.com
License: MIT
Platform: UNKNOWN
License-File: LICENSE
Requires-Dist: PyQt5 (>=5.8)
Requires-Dist: simplePyQt5 (>=0.0.1)
Requires-Dist: pyqt-file-list-widget (>=0.0.1)
Requires-Dist: pyqt-svg-icon-pushbutton (>=0.0.1)
